sqlrustler-0.1.0.dist-info/METADATA
sqlrustler-0.1.0.dist-info/WHEEL
sqlrustler-0.1.0.dist-info/licenses/LICENSE
sqlrustler/F.py
sqlrustler/Q.py
sqlrustler/__init__.py
sqlrustler/adaptor.py
sqlrustler/builders.py
sqlrustler/enum.py
sqlrustler/exceptions.py
sqlrustler/express.py
sqlrustler/expressions.py
sqlrustler/field.py
sqlrustler/model.py
sqlrustler/parser.py
sqlrustler/py.typed
sqlrustler/queryset.py
sqlrustler/sqlrustler.cpython-310-darwin.so
sqlrustler/sqlrustler.py
sqlrustler/window.py
sqlrustler-0.1.0.dist-info/RECORD
