Metadata-Version: 2.4
Name: sqlrustler
Version: 0.1.0
Classifier: Programming Language :: Rust
Classifier: Programming Language :: Python :: Implementation :: CPython
Classifier: Programming Language :: Python :: Implementation :: PyPy
License-File: LICENSE
Summary: A lightweight, high-performance Object-Relational Mapping (ORM) library for Python
Author-email: Martin Dang <vannghiem848@gmail.com>
Requires-Python: >=3.10
